{
  "version": "V4.4-decision-audit-pack",
  "generated_at": "2026-05-21T07:41:17.866594+00:00",
  "source_file": "resultados.json",
  "score_kind": "v4_2_deep_stacking_meta_score",
  "lambda_used": 0.7,
  "k": 10,
  "pool_size": 10,
  "pool_entropy": 0.52203,
  "average_pairwise_jaccard_original": 0.619048,
  "average_pairwise_jaccard_diversified": 0.619048,
  "unique_numbers_original_top_k": 9,
  "unique_numbers_diversified": 9,
  "diversity_gain": 0.0,
  "diversified_combinations": [
    {
      "rank_diversified": 1,
      "rank_original": 1,
      "numbers": [
        14,
        19,
        21,
        25,
        31,
        33
      ],
      "original_score": 82.476,
      "normalized_score": 1.0,
      "mmr_score": 1.0,
      "max_overlap_with_previous": 0,
      "max_jaccard_with_previous": 0.0,
      "selection_reason": "top_rank_anchor"
    },
    {
      "rank_diversified": 2,
      "rank_original": 9,
      "numbers": [
        9,
        14,
        19,
        25,
        31,
        32
      ],
      "original_score": 81.3921,
      "normalized_score": 0.044348,
      "mmr_score": -0.118956,
      "max_overlap_with_previous": 4,
      "max_jaccard_with_previous": 0.5,
      "selection_reason": "mmr_selected"
    },
    {
      "rank_diversified": 3,
      "rank_original": 2,
      "numbers": [
        9,
        14,
        19,
        21,
        25,
        31
      ],
      "original_score": 82.3348,
      "normalized_score": 0.875507,
      "mmr_score": 0.398569,
      "max_overlap_with_previous": 5,
      "max_jaccard_with_previous": 0.714286,
      "selection_reason": "overlap_relaxed"
    },
    {
      "rank_diversified": 4,
      "rank_original": 3,
      "numbers": [
        9,
        14,
        19,
        25,
        31,
        33
      ],
      "original_score": 82.009,
      "normalized_score": 0.588256,
      "mmr_score": 0.197494,
      "max_overlap_with_previous": 5,
      "max_jaccard_with_previous": 0.714286,
      "selection_reason": "overlap_relaxed"
    },
    {
      "rank_diversified": 5,
      "rank_original": 4,
      "numbers": [
        14,
        19,
        21,
        25,
        31,
        32
      ],
      "original_score": 81.8853,
      "normalized_score": 0.479192,
      "mmr_score": 0.121149,
      "max_overlap_with_previous": 5,
      "max_jaccard_with_previous": 0.714286,
      "selection_reason": "overlap_relaxed"
    },
    {
      "rank_diversified": 6,
      "rank_original": 5,
      "numbers": [
        1,
        14,
        19,
        21,
        25,
        31
      ],
      "original_score": 81.7227,
      "normalized_score": 0.335831,
      "mmr_score": 0.020796,
      "max_overlap_with_previous": 5,
      "max_jaccard_with_previous": 0.714286,
      "selection_reason": "overlap_relaxed"
    },
    {
      "rank_diversified": 7,
      "rank_original": 6,
      "numbers": [
        9,
        14,
        19,
        21,
        25,
        33
      ],
      "original_score": 81.5992,
      "normalized_score": 0.226944,
      "mmr_score": -0.055425,
      "max_overlap_with_previous": 5,
      "max_jaccard_with_previous": 0.714286,
      "selection_reason": "overlap_relaxed"
    },
    {
      "rank_diversified": 8,
      "rank_original": 7,
      "numbers": [
        14,
        19,
        25,
        31,
        32,
        33
      ],
      "original_score": 81.5715,
      "normalized_score": 0.202522,
      "mmr_score": -0.072521,
      "max_overlap_with_previous": 5,
      "max_jaccard_with_previous": 0.714286,
      "selection_reason": "overlap_relaxed"
    },
    {
      "rank_diversified": 9,
      "rank_original": 8,
      "numbers": [
        14,
        19,
        21,
        31,
        32,
        33
      ],
      "original_score": 81.4488,
      "normalized_score": 0.09434,
      "mmr_score": -0.148248,
      "max_overlap_with_previous": 5,
      "max_jaccard_with_previous": 0.714286,
      "selection_reason": "overlap_relaxed"
    },
    {
      "rank_diversified": 10,
      "rank_original": 10,
      "numbers": [
        1,
        14,
        19,
        25,
        31,
        33
      ],
      "original_score": 81.3418,
      "normalized_score": 0.0,
      "mmr_score": -0.214286,
      "max_overlap_with_previous": 5,
      "max_jaccard_with_previous": 0.714286,
      "selection_reason": "overlap_relaxed"
    }
  ],
  "overlap_matrix": [
    [
      1.0,
      0.5,
      0.714286,
      0.714286,
      0.714286,
      0.714286,
      0.714286,
      0.714286,
      0.714286,
      0.714286
    ],
    [
      0.5,
      1.0,
      0.714286,
      0.714286,
      0.714286,
      0.5,
      0.5,
      0.714286,
      0.5,
      0.5
    ],
    [
      0.714286,
      0.714286,
      1.0,
      0.714286,
      0.714286,
      0.714286,
      0.714286,
      0.5,
      0.5,
      0.5
    ],
    [
      0.714286,
      0.714286,
      0.714286,
      1.0,
      0.5,
      0.5,
      0.714286,
      0.714286,
      0.5,
      0.714286
    ],
    [
      0.714286,
      0.714286,
      0.714286,
      0.5,
      1.0,
      0.714286,
      0.5,
      0.714286,
      0.714286,
      0.5
    ],
    [
      0.714286,
      0.5,
      0.714286,
      0.5,
      0.714286,
      1.0,
      0.5,
      0.5,
      0.5,
      0.714286
    ],
    [
      0.714286,
      0.5,
      0.714286,
      0.714286,
      0.5,
      0.5,
      1.0,
      0.5,
      0.5,
      0.5
    ],
    [
      0.714286,
      0.714286,
      0.5,
      0.714286,
      0.714286,
      0.5,
      0.5,
      1.0,
      0.714286,
      0.714286
    ],
    [
      0.714286,
      0.5,
      0.5,
      0.5,
      0.714286,
      0.5,
      0.5,
      0.714286,
      1.0,
      0.5
    ],
    [
      0.714286,
      0.5,
      0.5,
      0.714286,
      0.5,
      0.714286,
      0.5,
      0.714286,
      0.5,
      1.0
    ]
  ],
  "quality_notes": [
    "High overlap detected in current top_combinations.",
    "Top combinations use a narrow number pool; consider reviewing generator diversity.",
    "MMR could not improve overlap using only top_combinations."
  ]
}